sphinxcontrib_opendataservices_jsonschema-0.7.1-py3.12-nspkg.pth
sphinxcontrib/jsonschema.py
tests/__init__.py
tests/test_directive.py
tests/test_jsonschema.py
sphinxcontrib_opendataservices_jsonschema-0.7.1.dist-info/LICENSE
sphinxcontrib_opendataservices_jsonschema-0.7.1.dist-info/METADATA
sphinxcontrib_opendataservices_jsonschema-0.7.1.dist-info/WHEEL
sphinxcontrib_opendataservices_jsonschema-0.7.1.dist-info/namespace_packages.txt
sphinxcontrib_opendataservices_jsonschema-0.7.1.dist-info/top_level.txt
sphinxcontrib_opendataservices_jsonschema-0.7.1.dist-info/RECORD
