Metadata-Version: 2.1
Name: sphinxcontrib-opendataservices-jsonschema
Version: 0.7.1
Summary: Sphinx extension to define data structure using JSON Schema
Home-page: https://github.com/OpenDataServices/sphinxcontrib-opendataservices-jsonschema
Author: Takeshi KOMIYA & Open Data Services Co-operative
Author-email: code@opendataservices.coop
License: BSD
Platform: any
Classifier: Development Status :: 3 - Alpha
Classifier: Environment :: Console
Classifier: Framework :: Sphinx :: Extension
Classifier: Intended Audience :: Developers
Classifier: License :: OSI Approved :: BSD License
Classifier: Operating System :: OS Independent
Classifier: Programming Language :: Python
Classifier: Programming Language :: Python :: 3
Classifier: Programming Language :: Python :: 3.8
Classifier: Programming Language :: Python :: 3.9
Classifier: Programming Language :: Python :: 3.10
Classifier: Topic :: Documentation
Classifier: Topic :: Documentation :: Sphinx
Requires-Python: >=3.8
License-File: LICENSE
Requires-Dist: docutils
Requires-Dist: jsonref
Requires-Dist: jsonpointer
Requires-Dist: myst-parser
Requires-Dist: referencing
Requires-Dist: jscc
Provides-Extra: test
Requires-Dist: flake8<6; extra == "test"
Requires-Dist: lxml; extra == "test"
Requires-Dist: defusedxml; extra == "test"
Requires-Dist: pytest; extra == "test"
